naneos/__init__.py
naneos/py.typed
naneos/iotweb/__init__.py
naneos/iotweb/naneos_upload_thread.py
naneos/iotweb/download/__init__.py
naneos/iotweb/download/downloader.py
naneos/logger/__init__.py
naneos/logger/custom_logger.py
naneos/manager/__init__.py
naneos/manager/naneos_device_manager.py
naneos/partector/__init__.py
naneos/partector/partector1.py
naneos/partector/partector2.py
naneos/partector/partector2_pro.py
naneos/partector/partector2_pro_cs.py
naneos/partector/partector_serial_manager.py
naneos/partector/scanPartector.py
naneos/partector/blueprints/__init__.py
naneos/partector/blueprints/_data_structure.py
naneos/partector/blueprints/_partectorCheckerThread.py
naneos/partector/blueprints/_partector_blueprint.py
naneos/partector/blueprints/_partector_defaults.py
naneos/partector_ble/__init__.py
naneos/partector_ble/partector_ble_connection.py
naneos/partector_ble/partector_ble_decoder.py
naneos/partector_ble/partector_ble_manager.py
naneos/partector_ble/partector_ble_scanner.py
naneos/partector_ble/decoder/__init__.py
naneos/partector_ble/decoder/partectod_ble_decoder_aux_error.py
naneos/partector_ble/decoder/partector_ble_decoder_aux.py
naneos/partector_ble/decoder/partector_ble_decoder_blueprint.py
naneos/partector_ble/decoder/partector_ble_decoder_size.py
naneos/partector_ble/decoder/partector_ble_decoder_std.py
naneos/protobuf/__init__.py
naneos/protobuf/protoV1.proto
naneos/protobuf/protoV1_pb2.py
naneos/protobuf/protoV1_pb2.pyi
naneos/protobuf/protobuf.py
naneos/serial_utils/__init__.py
naneos/serial_utils/list_serial_ports.py
naneos/utils/send_commands.py
naneos_devices-1.1.16.dist-info/METADATA
naneos_devices-1.1.16.dist-info/WHEEL
naneos_devices-1.1.16.dist-info/licenses/LICENSE.txt
naneos_devices-1.1.16.dist-info/RECORD
