Metadata-Version: 2.4
Name: naneos-devices
Version: 1.1.16
Summary: naneos particle solutions gmbh python backend
Project-URL: Repository, https://github.com/naneos-org/python-naneos-devices
Project-URL: Documentation, https://naneos-org.github.io/python-naneos-devices/
Author-email: Mario Huegi <mario.huegi@naneos.com>
License-File: LICENSE.txt
Classifier: Development Status :: 5 - Production/Stable
Classifier: Environment :: Console
Classifier: Intended Audience :: Healthcare Industry
Classifier: Intended Audience :: Science/Research
Classifier: License :: OSI Approved :: MIT License
Classifier: Operating System :: OS Independent
Classifier: Programming Language :: Python :: 3.10
Classifier: Programming Language :: Python :: 3.11
Classifier: Programming Language :: Python :: 3.12
Classifier: Programming Language :: Python :: 3.13
Classifier: Topic :: Scientific/Engineering
Requires-Python: <3.14,>=3.10
Requires-Dist: bleak>=0.22.3
Requires-Dist: influxdb-client[ciso]>=1.48.0
Requires-Dist: pandas>=2.2.3
Requires-Dist: protobuf>=6.33.0
Requires-Dist: pyserial>=3.5
Requires-Dist: requests>=2.32.3
Requires-Dist: rich>=14.0.0
Requires-Dist: typer>=0.15.2
Provides-Extra: test
Requires-Dist: coverage; extra == 'test'
Requires-Dist: hypothesis; extra == 'test'
Requires-Dist: pytest; extra == 'test'
